AUTHORS.rst
CHANGELOG.rst
MANIFEST.in
README.rst
setup.py
friends/__init__.py
friends/forms.py
friends/models.py
friends/signals.py
friends/urls.py
friends/views.py
friends/management/__init__.py
friends/management/__init__.pyc
friends/management/commands/__init__.py
friends/management/commands/find_duplicate_memberfriend.py
friends/migrations/0001_initial.py
friends/migrations/0001_initial.pyc
friends/migrations/0002_auto__add_field_directmessage_root_direct_message.py
friends/migrations/0002_auto__add_field_directmessage_root_direct_message.pyc
friends/migrations/0003_auto__chg_field_directmessage_root_direct_message.py
friends/migrations/0003_auto__chg_field_directmessage_root_direct_message.pyc
friends/migrations/0004_auto__add_field_memberfriend_created.py
friends/migrations/0004_auto__add_field_memberfriend_created.pyc
friends/migrations/__init__.py
friends/migrations/__init__.pyc
friends/templates/basic/friends/friend_request_accepted.html
friends/templates/basic/friends/friend_request_email.html
friends/templates/basic/friends/friend_request_form.html
friends/templates/basic/friends/inbox.html
friends/templates/basic/friends/member_detail.html
friends/templates/basic/friends/message_view.html
friends/templates/basic/friends/my_friend_requests.html
friends/templates/basic/friends/my_friends.html
friends/templates/basic/friends/reply_to_direct_message.html
friends/templates/basic/friends/send_direct_message.html
friends/templates/basic/friends/inclusion_tags/direct_message.html
friends/templates/basic/friends/inclusion_tags/my_friends.html
friends/templates/basic/friends/inclusion_tags/suggested_friends.html
friends/templatetags/__init__.py
friends/templatetags/__init__.pyc
friends/templatetags/friends_tags.py
jmbo_friends.egg-info/PKG-INFO
jmbo_friends.egg-info/SOURCES.txt
jmbo_friends.egg-info/dependency_links.txt
jmbo_friends.egg-info/not-zip-safe
jmbo_friends.egg-info/requires.txt
jmbo_friends.egg-info/top_level.txt